LICENSE
MANIFEST.in
README.md
setup.py
cleanup_later/__init__.py
cleanup_later/middleware.py
cleanup_later/models.py
cleanup_later/management/__init__.py
cleanup_later/management/commands/__init__.py
cleanup_later/management/commands/cleanup_later.py
cleanup_later/migrations/0001_initial.py
cleanup_later/migrations/__init__.py
django_cleanup_later.egg-info/PKG-INFO
django_cleanup_later.egg-info/SOURCES.txt
django_cleanup_later.egg-info/dependency_links.txt
django_cleanup_later.egg-info/top_level.txt