Metadata-Version: 2.1
Name: django-cleanup-later
Version: 0.1
Summary: A quick, rough around the edges Django application to remember and remove temporary files.
Home-page: https://www.bravasoftware.com/
Author: Mark Skelton
Author-email: mark@bravasoftware.com
License: MIT License
Platform: UNKNOWN
Classifier: Environment :: Web Environment
Classifier: Framework :: Django
Classifier: Framework :: Django :: 2.2
Classifier: Intended Audience :: Developers
Classifier: License :: OSI Approved :: MIT License
Classifier: Operating System :: OS Independent
Classifier: Programming Language :: Python
Classifier: Programming Language :: Python :: 3.7
Classifier: Topic :: Internet :: WWW/HTTP
Classifier: Topic :: Internet :: WWW/HTTP :: Dynamic Content
